[
{"title": "Data Structures and Algorithms with Object-Oriented Design Patterns in Python "},
{"title": "Dive Into Python 3 "},
{"title": "Foundations of Python Network Programming "},
{"title": "Free Python books "},
{"title": "FreeTechBooks: Python Scripting Language "},
{"title": "How to Think Like a Computer Scientist: Learning with Python "},
{"title": "An Introduction to Python "},
{"title": "Making Use of Python "},
{"title": "Practical Python "},
{"title": "Pro Python System Administration "},
{"title": "Programming in Python 3 (Second Edition) "},
{"title": "Python 2.1 Bible "},
{"title": "Python 3 Object Oriented Programming "},
{"title": "Python Language Reference Manual "},
{"title": "Python Programming with the Java Class Libraries: A Tutorial for Building Web and Enterprise Applications with Jython "},
{"title": "Sams Teach Yourself Python in 24 Hours "},
{"title": "Text Processing in Python "},
{"title": "XML Processing with Python "}
]